mm_apt/__init__.py
mm_apt/account.py
mm_apt/ans.py
mm_apt/balance.py
mm_apt/coin.py
mm_apt/py.typed
mm_apt/retry.py
mm_apt-0.5.1.dist-info/METADATA
mm_apt-0.5.1.dist-info/WHEEL
mm_apt-0.5.1.dist-info/RECORD
