Metadata-Version: 2.4
Name: mm-apt
Version: 0.5.1
Requires-Python: >=3.13
Requires-Dist: mm-web3~=0.5.6
